opentelemetry/instrumentation/langchain/__init__.py
opentelemetry/instrumentation/langchain/callback_handler.py
opentelemetry/instrumentation/langchain/config.py
opentelemetry/instrumentation/langchain/semconv_ai.py
opentelemetry/instrumentation/langchain/span_utils.py
opentelemetry/instrumentation/langchain/utils.py
opentelemetry/instrumentation/langchain/vendor_detection.py
opentelemetry/instrumentation/langchain/version.py
splunk_otel_instrumentation_langchain-0.1.7.dist-info/METADATA
splunk_otel_instrumentation_langchain-0.1.7.dist-info/WHEEL
splunk_otel_instrumentation_langchain-0.1.7.dist-info/entry_points.txt
splunk_otel_instrumentation_langchain-0.1.7.dist-info/licenses/LICENSE
splunk_otel_instrumentation_langchain-0.1.7.dist-info/RECORD
