Metadata-Version: 2.4
Name: splunk-otel-instrumentation-langchain
Version: 0.1.7
Summary: OpenTelemetry Official Langchain instrumentation
Project-URL: Homepage, https://github.com/open-telemetry/opentelemetry-python-contrib/tree/main/instrumentation-genai/opentelemetry-instrumentation-langchain
Project-URL: Repository, https://github.com/open-telemetry/opentelemetry-python-contrib
Author-email: OpenTelemetry Authors <cncf-opentelemetry-contributors@lists.cncf.io>
License-Expression: Apache-2.0
License-File: LICENSE
Classifier: Development Status :: 4 - Beta
Classifier: Intended Audience :: Developers
Classifier: License :: OSI Approved :: Apache Software License
Classifier: Programming Language :: Python
Classifier: Programming Language :: Python :: 3.9
Classifier: Programming Language :: Python :: 3.10
Classifier: Programming Language :: Python :: 3.11
Classifier: Programming Language :: Python :: 3.12
Classifier: Programming Language :: Python :: 3.13
Requires-Python: >=3.9
Requires-Dist: opentelemetry-api~=1.38.0.dev0
Requires-Dist: opentelemetry-instrumentation~=0.59b0.dev0
Requires-Dist: opentelemetry-semantic-conventions~=0.59b0.dev0
Requires-Dist: splunk-otel-util-genai>=0.1.4
Provides-Extra: instruments
Requires-Dist: langchain>=0.3.21; extra == 'instruments'
Provides-Extra: test
Requires-Dist: flaky>=3.8.1; extra == 'test'
Requires-Dist: langchain-core>=1.0.0; extra == 'test'
Requires-Dist: langchain-openai>=1.0.0; extra == 'test'
Requires-Dist: pytest-recording>=0.13.0; extra == 'test'
Requires-Dist: pyyaml>=6.0.0; extra == 'test'
Requires-Dist: vcrpy>=7.0.0; extra == 'test'
